{
  "data": {
    "userAuth": {
      "credit": {
        "tasks": [
          {
            "id": 39265747,
            "task_id": 12,
            "task_name": "签到",
            "task_info": "",
            "task_url": "",
            "credit_num": "5",
            "contents": null,
            "conditions": "<CON_SIGN:1>",
            "task_type": "sign",
            "status": "2"
          }
        ],
        "staticTasks": [
          {
            "id": 15,
            "name": "违规一次",
            "task_type_name": null,
            "credit_num": "-15",
            "contents": null,
            "button": null
          },
          {
            "id": 16,
            "name": "成功保留一次",
            "task_type_name": null,
            "credit_num": "2",
            "contents": null,
            "button": null
          },
          {
            "id": 17,
            "name": "成功监督一次",
            "task_type_name": null,
            "credit_num": "15",
            "contents": null,
            "button": null
          },
          {
            "id": 18,
            "name": "学习奖励积分",
            "task_type_name": null,
            "credit_num": "5",
            "contents": null,
            "button": null
          },
          {
            "id": 19,
            "name": "每天最多获取",
            "task_type_name": null,
            "credit_num": "40",
            "contents": null,
            "button": null
          }
        ]
      }
    }
  }
}